Workbook

Sheet Assumptions
A1: 3-STATEMENT FINANCIAL MODEL — ASSUMPTIONS & DRIVERS
A2: Blue = inputs | Black = formulas | Amounts in ₹ Lakhs | Source: Management Estimates
A3: Assumption / Driver | B3: Unit | C3: FY2023 | D3: FY2024 | E3: FY2025E | F3: FY2026E | G3: FY2027E
A4: 1. Revenue Drivers
A5: Revenue (₹ Lakhs) | B5: ₹L | C5: 480 | D5: 560 | E5: 650 | F5: 760 | G5: 890
A6: Revenue Growth YoY | B6: % | C6: — | D6: =(D5-C5)/C5 | E6: =(E5-D5)/D5 | F6: =(F5-E5)/E5 | G6: =(G5-F5)/F5
A7: 2. P&L Margin Drivers
A8: COGS as % of Revenue | B8: % | C8: 0.58 | D8: 0.57 | E8: 0.56 | F8: 0.55 | G8: 0.54
A9: Gross Margin % | B9: % | C9: =1-C8 | D9: =1-D8 | E9: =1-E8 | F9: =1-F8 | G9: =1-G8
A10: Operating Expenses (% Rev) | B10: % | C10: 0.22 | D10: 0.21 | E10: 0.2 | F10: 0.19 | G10: 0.18
A11: EBITDA Margin % | B11: % | C11: =C9-C10 | D11: =D9-D10 | E11: =E9-E10 | F11: =F9-F10 | G11: =G9-G10
A12: Depreciation (% of Gross FA) | B12: % | C12: 0.1 | D12: 0.1 | E12: 0.1 | F12: 0.1 | G12: 0.1
A13: Interest Rate on Debt | B13: % | C13: 0.085 | D13: 0.085 | E13: 0.08 | F13: 0.075 | G13: 0.075
A14: Effective Tax Rate | B14: % | C14: 0.25 | D14: 0.25 | E14: 0.25 | F14: 0.25 | G14: 0.25
A15: 3. Balance Sheet Drivers
A16: Receivable Days (DSO) | B16: days | C16: 60 | D16: 58 | E16: 55 | F16: 52 | G16: 50
A17: Inventory Days (DIO) | B17: days | C17: 45 | D17: 43 | E17: 40 | F17: 38 | G17: 36
A18: Payable Days (DPO) | B18: days | C18: 38 | D18: 40 | E18: 42 | F18: 44 | G18: 45
A19: Capex (₹ Lakhs) | B19: ₹L | C19: 30 | D19: 35 | E19: 45 | F19: 50 | G19: 55
A20: Opening Gross FA (₹ Lakhs) | B20: ₹L | C20: 200 | D20: =C20+C19 | E20: =D20+D19 | F20: =E20+E19 | G20: =F20+F19
A21: Opening Debt (₹ Lakhs) | B21: ₹L | C21: 100
A22: Debt Repaid per Year (₹ Lakhs) | B22: ₹L | C22: 10 | D22: 10 | E22: 10 | F22: 10 | G22: 10
A23: New Debt Raised (₹ Lakhs) | B23: ₹L | C23: 0 | D23: 20 | E23: 15 | F23: 10 | G23: 0
A24: Dividend Payout Ratio | B24: % | C24: 0.2 | D24: 0.2 | E24: 0.25 | F24: 0.25 | G24: 0.3
A25: Opening Cash & Equivalents | B25: ₹L | C25: 40

Sheet Income Statement
A1: INCOME STATEMENT
A2: ₹ Lakhs | Linked to Assumptions sheet | Green text = cross-sheet links
A3: Line Item | B3: Note | C3: FY2023 | D3: FY2024 | E3: FY2025E | F3: FY2026E | G3: FY2027E
A4: Revenue (₹ Lakhs) | B4: AS1 | C4: =Assumptions!C5 | D4: =Assumptions!D5 | E4: =Assumptions!E5 | F4: =Assumptions!F5 | G4: =Assumptions!G5
A5: Less: Cost of Goods Sold | B5: AS2 | C5: =-Assumptions!C8*Assumptions!C5 | D5: =-Assumptions!D8*Assumptions!D5 | E5: =-Assumptions!E8*Assumptions!E5 | F5: =-Assumptions!F8*Assumptions!F5 | G5: =-Assumptions!G8*Assumptions!G5
A6: GROSS PROFIT | C6: =C4+C5 | D6: =D4+D5 | E6: =E4+E5 | F6: =F4+F5 | G6: =G4+G5
A7: Gross Margin % | C7: =C6/C4 | D7: =D6/D4 | E7: =E6/E4 | F7: =F6/F4 | G7: =G6/G4
A8: Less: Operating Expenses | B8: AS3 | C8: =-Assumptions!C10*Assumptions!C5 | D8: =-Assumptions!D10*Assumptions!D5 | E8: =-Assumptions!E10*Assumptions!E5 | F8: =-Assumptions!F10*Assumptions!F5 | G8: =-Assumptions!G10*Assumptions!G5
A9: EBITDA | C9: =C6+C8 | D9: =D6+D8 | E9: =E6+E8 | F9: =F6+F8 | G9: =G6+G8
A10: EBITDA Margin % | C10: =C9/C4 | D10: =D9/D4 | E10: =E9/E4 | F10: =F9/F4 | G10: =G9/G4
A11: Less: Depreciation & Amortisation | B11: AS4 | C11: =-Assumptions!C12*Assumptions!C20 | D11: =-Assumptions!D12*Assumptions!D20 | E11: =-Assumptions!E12*Assumptions!E20 | F11: =-Assumptions!F12*Assumptions!F20 | G11: =-Assumptions!G12*Assumptions!G20
A12: EBIT (Operating Profit) | C12: =C9+C11 | D12: =D9+D11 | E12: =E9+E11 | F12: =F9+F11 | G12: =G9+G11
A13: EBIT Margin % | C13: =C12/C4 | D13: =D12/D4 | E13: =E12/E4 | F13: =F12/F4 | G13: =G12/G4
A14: Less: Interest Expense | B14: AS5 | C14: =-Assumptions!C13*Assumptions!C21 | D14: =-Assumptions!D13*Assumptions!D21 | E14: =-Assumptions!E13*Assumptions!E21 | F14: =-Assumptions!F13*Assumptions!F21 | G14: =-Assumptions!G13*Assumptions!G21
A15: EBT (Profit Before Tax) | C15: =C12+C14 | D15: =D12+D14 | E15: =E12+E14 | F15: =F12+F14 | G15: =G12+G14
A16: Less: Income Tax | B16: AS6 | C16: =-MAX(C15,0)*Assumptions!C14 | D16: =-MAX(D15,0)*Assumptions!D14 | E16: =-MAX(E15,0)*Assumptions!E14 | F16: =-MAX(F15,0)*Assumptions!F14 | G16: =-MAX(G15,0)*Assumptions!G14
A17: NET PROFIT AFTER TAX (PAT) | C17: =C15+C16 | D17: =D15+D16 | E17: =E15+E16 | F17: =F15+F16 | G17: =G15+G16
A18: Net Profit Margin % | C18: =C17/C4 | D18: =D17/D4 | E18: =E17/E4 | F18: =F17/F4 | G18: =G17/G4
A19: Less: Dividends Paid | B19: AS7 | C19: =-MAX(C17,0)*Assumptions!C24 | D19: =-MAX(D17,0)*Assumptions!D24 | E19: =-MAX(E17,0)*Assumptions!E24 | F19: =-MAX(F17,0)*Assumptions!F24 | G19: =-MAX(G17,0)*Assumptions!G24
A20: Retained Earnings Addition | C20: =C17+C19 | D20: =D17+D19 | E20: =E17+E19 | F20: =F17+F19 | G20: =G17+G19

Sheet Balance Sheet
A1: BALANCE SHEET
A2: ₹ Lakhs | Fully linked to IS and CF | Check row verifies Assets = Liabilities + Equity
A3: Line Item | B3: Note | C3: FY2023 | D3: FY2024 | E3: FY2025E | F3: FY2026E | G3: FY2027E
A4: ASSETS
A5: Current Assets
A6: Trade Receivables | B6: DSO | C6: =Assumptions!C16/365*'Income Statement'!C4 | D6: =Assumptions!D16/365*'Income Statement'!D4 | E6: =Assumptions!E16/365*'Income Statement'!E4 | F6: =Assumptions!F16/365*'Income Statement'!F4 | G6: =Assumptions!G16/365*'Income Statement'!G4
A7: Inventories | B7: DIO | C7: =Assumptions!C17/365*(-'Income Statement'!C5) | D7: =Assumptions!D17/365*(-'Income Statement'!D5) | E7: =Assumptions!E17/365*(-'Income Statement'!E5) | F7: =Assumptions!F17/365*(-'Income Statement'!F5) | G7: =Assumptions!G17/365*(-'Income Statement'!G5)
A8: Other Current Assets | C8: 10 | D8: 12 | E8: 14 | F8: 16 | G8: 18
A9: Cash & Cash Equivalents | B9: CF | C9: =Assumptions!C25 | D9: ='Cash Flow Statement'!D22 | E9: ='Cash Flow Statement'!E22 | F9: ='Cash Flow Statement'!F22 | G9: ='Cash Flow Statement'!G22
A10: TOTAL CURRENT ASSETS | C10: =SUM(C6:C9) | D10: =SUM(D6:D9) | E10: =SUM(E6:E9) | F10: =SUM(F6:F9) | G10: =SUM(G6:G9)
A11: Non-Current Assets
A12: Gross Fixed Assets | B12: Capex | C12: =Assumptions!C20+Assumptions!C19 | D12: =Assumptions!D20+Assumptions!D19 | E12: =Assumptions!E20+Assumptions!E19 | F12: =Assumptions!F20+Assumptions!F19 | G12: =Assumptions!G20+Assumptions!G19
A13: Less: Accumulated Depreciation | C13: =-Assumptions!C12*Assumptions!C20 | D13: =C13-Assumptions!D12*Assumptions!D20 | E13: =D13-Assumptions!E12*Assumptions!E20 | F13: =E13-Assumptions!F12*Assumptions!F20 | G13: =F13-Assumptions!G12*Assumptions!G20
A14: Net Fixed Assets (Net Block) | C14: =C12+C13 | D14: =D12+D13 | E14: =E12+E13 | F14: =F12+F13 | G14: =G12+G13
A15: Other Non-Current Assets | C15: 15 | D15: 15 | E15: 20 | F15: 20 | G15: 20
A16: TOTAL NON-CURRENT ASSETS | C16: =C14+C15 | D16: =D14+D15 | E16: =E14+E15 | F16: =F14+F15 | G16: =G14+G15
A17: TOTAL ASSETS | C17: =C10+C16 | D17: =D10+D16 | E17: =E10+E16 | F17: =F10+F16 | G17: =G10+G16
A18: LIABILITIES & EQUITY
A19: Current Liabilities
A20: Trade Payables | B20: DPO | C20: =Assumptions!C18/365*(-'Income Statement'!C5) | D20: =Assumptions!D18/365*(-'Income Statement'!D5) | E20: =Assumptions!E18/365*(-'Income Statement'!E5) | F20: =Assumptions!F18/365*(-'Income Statement'!F5) | G20: =Assumptions!G18/365*(-'Income Statement'!G5)
A21: Other Current Liabilities | C21: 8 | D21: 9 | E21: 10 | F21: 11 | G21: 12
A22: Current Portion of Debt | B22: Repmt | C22: =Assumptions!C22 | D22: =Assumptions!D22 | E22: =Assumptions!E22 | F22: =Assumptions!F22 | G22: =Assumptions!G22
A23: TOTAL CURRENT LIABILITIES | C23: =SUM(C20:C22) | D23: =SUM(D20:D22) | E23: =SUM(E20:E22) | F23: =SUM(F20:F22) | G23: =SUM(G20:G22)
A24: Non-Current Liabilities
A25: Long-Term Debt | C25: =Assumptions!C21 | D25: =C25-Assumptions!D22+Assumptions!D23 | E25: =D25-Assumptions!E22+Assumptions!E23 | F25: =E25-Assumptions!F22+Assumptions!F23 | G25: =F25-Assumptions!G22+Assumptions!G23
A26: TOTAL NON-CURRENT LIABILITIES | C26: =C25 | D26: =D25 | E26: =E25 | F26: =F25 | G26: =G25
A27: Shareholders' Equity
A28: Share Capital | B28: Stub | C28: 50 | D28: 50 | E28: 50 | F28: 50 | G28: 50
A29: Retained Earnings | C29: ='Income Statement'!C20 | D29: =C29+'Income Statement'!D20 | E29: =D29+'Income Statement'!E20 | F29: =E29+'Income Statement'!F20 | G29: =F29+'Income Statement'!G20
A30: TOTAL EQUITY | C30: =C28+C29 | D30: =D28+D29 | E30: =E28+E29 | F30: =F28+F29 | G30: =G28+G29
A31: TOTAL LIABILITIES + EQUITY | C31: =C23+C26+C30 | D31: =D23+D26+D30 | E31: =E23+E26+E30 | F31: =F23+F26+F30 | G31: =G23+G26+G30
A32: BS Check = Assets minus L+E (must = 0) | C32: =C17-C31 | D32: =D17-D31 | E32: =E17-E31 | F32: =F17-F31 | G32: =G17-G31

Sheet Cash Flow Statement
A1: CASH FLOW STATEMENT — INDIRECT METHOD
A2: ₹ Lakhs | Indirect method | Closing Cash links back to Balance Sheet
A3: Line Item | B3: Note | C3: FY2023 | D3: FY2024 | E3: FY2025E | F3: FY2026E | G3: FY2027E
A4: A. CASH FROM OPERATIONS (CFO)
A5: Net Profit After Tax (PAT) | B5: IS | C5: ='Income Statement'!C17 | D5: ='Income Statement'!D17 | E5: ='Income Statement'!E17 | F5: ='Income Statement'!F17 | G5: ='Income Statement'!G17
A6: Add: Depreciation & Amortisation | B6: IS | C6: =-'Income Statement'!C11 | D6: =-'Income Statement'!D11 | E6: =-'Income Statement'!E11 | F6: =-'Income Statement'!F11 | G6: =-'Income Statement'!G11
A7: Working Capital Changes
A8: (Increase)/Decrease in Receivables | B8: WC | C8: =0 | D8: =-('Balance Sheet'!D6-'Balance Sheet'!C6) | E8: =-('Balance Sheet'!E6-'Balance Sheet'!D6) | F8: =-('Balance Sheet'!F6-'Balance Sheet'!E6) | G8: =-('Balance Sheet'!G6-'Balance Sheet'!F6)
A9: (Increase)/Decrease in Inventories | B9: WC | C9: =0 | D9: =-('Balance Sheet'!D7-'Balance Sheet'!C7) | E9: =-('Balance Sheet'!E7-'Balance Sheet'!D7) | F9: =-('Balance Sheet'!F7-'Balance Sheet'!E7) | G9: =-('Balance Sheet'!G7-'Balance Sheet'!F7)
A10: Increase/(Decrease) in Payables | B10: WC | C10: =0 | D10: ='Balance Sheet'!D20-'Balance Sheet'!C20 | E10: ='Balance Sheet'!E20-'Balance Sheet'!D20 | F10: ='Balance Sheet'!F20-'Balance Sheet'!E20 | G10: ='Balance Sheet'!G20-'Balance Sheet'!F20
A11: CASH FROM OPERATIONS (CFO) | C11: =SUM(C5:C10) | D11: =SUM(D5:D10) | E11: =SUM(E5:E10) | F11: =SUM(F5:F10) | G11: =SUM(G5:G10)
A12: B. CASH FROM INVESTING (CFI)
A13: Capital Expenditure (Capex) | B13: AS8 | C13: =-Assumptions!C19 | D13: =-Assumptions!D19 | E13: =-Assumptions!E19 | F13: =-Assumptions!F19 | G13: =-Assumptions!G19
A14: Proceeds from Asset Sales | C14: 0 | D14: 0 | E14: 0 | F14: 0 | G14: 0
A15: CASH FROM INVESTING (CFI) | C15: =SUM(C13:C14) | D15: =SUM(D13:D14) | E15: =SUM(E13:E14) | F15: =SUM(F13:F14) | G15: =SUM(G13:G14)
A16: C. CASH FROM FINANCING (CFF)
A17: Debt Raised | B17: AS9 | C17: =Assumptions!C23 | D17: =Assumptions!D23 | E17: =Assumptions!E23 | F17: =Assumptions!F23 | G17: =Assumptions!G23
A18: Debt Repaid | B18: AS10 | C18: =-Assumptions!C22 | D18: =-Assumptions!D22 | E18: =-Assumptions!E22 | F18: =-Assumptions!F22 | G18: =-Assumptions!G22
A19: Dividends Paid | B19: IS | C19: ='Income Statement'!C19 | D19: ='Income Statement'!D19 | E19: ='Income Statement'!E19 | F19: ='Income Statement'!F19 | G19: ='Income Statement'!G19
A20: CASH FROM FINANCING (CFF) | C20: =SUM(C17:C19) | D20: =SUM(D17:D19) | E20: =SUM(E17:E19) | F20: =SUM(F17:F19) | G20: =SUM(G17:G19)
A21: NET CHANGE IN CASH | C21: =C11+C15+C20 | D21: =D11+D15+D20 | E21: =E11+E15+E20 | F21: =F11+F15+F20 | G21: =G11+G15+G20
A22: Opening Cash Balance | C22: =Assumptions!C25 | D22: =C23 | E22: =D23 | F22: =E23 | G22: =F23
A23: Closing Cash Balance | C23: =C21+C22 | D23: =D21+D22 | E23: =E21+E22 | F23: =F21+F22 | G23: =G21+G22
A24: CF Check = CF Closing vs BS Cash (must = 0) | C24: =C23-'Balance Sheet'!C9 | D24: =D23-'Balance Sheet'!D9 | E24: =E23-'Balance Sheet'!E9 | F24: =F23-'Balance Sheet'!F9 | G24: =G23-'Balance Sheet'!G9

Sheet Ratio Dashboard
A1: KPI & RATIO DASHBOARD
A2: Fully linked from IS and BS | Green = improving | Red = deteriorating
A3: Metric | B3: FY2023 | C3: FY2024 | D3: FY2025E | E3: FY2026E | F3: FY2027E
A4: Profitability Ratios
A5: Gross Margin % | B5: ='Income Statement'!C7 | C5: ='Income Statement'!D7 | D5: ='Income Statement'!E7 | E5: ='Income Statement'!F7 | F5: ='Income Statement'!G7
A6: EBITDA Margin % | B6: ='Income Statement'!C10 | C6: ='Income Statement'!D10 | D6: ='Income Statement'!E10 | E6: ='Income Statement'!F10 | F6: ='Income Statement'!G10
A7: EBIT Margin % | B7: ='Income Statement'!C13 | C7: ='Income Statement'!D13 | D7: ='Income Statement'!E13 | E7: ='Income Statement'!F13 | F7: ='Income Statement'!G13
A8: Net Profit Margin % | B8: ='Income Statement'!C18 | C8: ='Income Statement'!D18 | D8: ='Income Statement'!E18 | E8: ='Income Statement'!F18 | F8: ='Income Statement'!G18
A9: Return on Equity (ROE) | B9: ='Income Statement'!C17/'Balance Sheet'!C30 | C9: ='Income Statement'!D17/'Balance Sheet'!D30 | D9: ='Income Statement'!E17/'Balance Sheet'!E30 | E9: ='Income Statement'!F17/'Balance Sheet'!F30 | F9: ='Income Statement'!G17/'Balance Sheet'!G30
A10: Return on Assets (ROA) | B10: ='Income Statement'!C17/'Balance Sheet'!C17 | C10: ='Income Statement'!D17/'Balance Sheet'!D17 | D10: ='Income Statement'!E17/'Balance Sheet'!E17 | E10: ='Income Statement'!F17/'Balance Sheet'!F17 | F10: ='Income Statement'!G17/'Balance Sheet'!G17
A11: Return on Capital (ROCE) | B11: ='Income Statement'!C12/('Balance Sheet'!C17-'Balance Sheet'!C23) | C11: ='Income Statement'!D12/('Balance Sheet'!D17-'Balance Sheet'!D23) | D11: ='Income Statement'!E12/('Balance Sheet'!E17-'Balance Sheet'!E23) | E11: ='Income Statement'!F12/('Balance Sheet'!F17-'Balance Sheet'!F23) | F11: ='Income Statement'!G12/('Balance Sheet'!G17-'Balance Sheet'!G23)
A12: Liquidity & Solvency Ratios
A13: Current Ratio | B13: ='Balance Sheet'!C10/'Balance Sheet'!C23 | C13: ='Balance Sheet'!D10/'Balance Sheet'!D23 | D13: ='Balance Sheet'!E10/'Balance Sheet'!E23 | E13: ='Balance Sheet'!F10/'Balance Sheet'!F23 | F13: ='Balance Sheet'!G10/'Balance Sheet'!G23
A14: Quick Ratio | B14: =('Balance Sheet'!C10-'Balance Sheet'!C7)/'Balance Sheet'!C23 | C14: =('Balance Sheet'!D10-'Balance Sheet'!D7)/'Balance Sheet'!D23 | D14: =('Balance Sheet'!E10-'Balance Sheet'!E7)/'Balance Sheet'!E23 | E14: =('Balance Sheet'!F10-'Balance Sheet'!F7)/'Balance Sheet'!F23 | F14: =('Balance Sheet'!G10-'Balance Sheet'!G7)/'Balance Sheet'!G23
A15: Debt-to-Equity | B15: =('Balance Sheet'!C25+'Balance Sheet'!C22)/'Balance Sheet'!C30 | C15: =('Balance Sheet'!D25+'Balance Sheet'!D22)/'Balance Sheet'!D30 | D15: =('Balance Sheet'!E25+'Balance Sheet'!E22)/'Balance Sheet'!E30 | E15: =('Balance Sheet'!F25+'Balance Sheet'!F22)/'Balance Sheet'!F30 | F15: =('Balance Sheet'!G25+'Balance Sheet'!G22)/'Balance Sheet'!G30
A16: Debt-to-EBITDA | B16: =('Balance Sheet'!C25+'Balance Sheet'!C22)/'Income Statement'!C9 | C16: =('Balance Sheet'!D25+'Balance Sheet'!D22)/'Income Statement'!D9 | D16: =('Balance Sheet'!E25+'Balance Sheet'!E22)/'Income Statement'!E9 | E16: =('Balance Sheet'!F25+'Balance Sheet'!F22)/'Income Statement'!F9 | F16: =('Balance Sheet'!G25+'Balance Sheet'!G22)/'Income Statement'!G9
A17: Interest Coverage (x) | B17: ='Income Statement'!C12/(-'Income Statement'!C14) | C17: ='Income Statement'!D12/(-'Income Statement'!D14) | D17: ='Income Statement'!E12/(-'Income Statement'!E14) | E17: ='Income Statement'!F12/(-'Income Statement'!F14) | F17: ='Income Statement'!G12/(-'Income Statement'!G14)
A18: Efficiency / Activity Ratios
A19: DSO (Receivable Days) | B19: =Assumptions!C16 | C19: =Assumptions!D16 | D19: =Assumptions!E16 | E19: =Assumptions!F16 | F19: =Assumptions!G16
A20: DIO (Inventory Days) | B20: =Assumptions!C17 | C20: =Assumptions!D17 | D20: =Assumptions!E17 | E20: =Assumptions!F17 | F20: =Assumptions!G17
A21: DPO (Payable Days) | B21: =Assumptions!C18 | C21: =Assumptions!D18 | D21: =Assumptions!E18 | E21: =Assumptions!F18 | F21: =Assumptions!G18
A22: Cash Conversion Cycle | B22: =Assumptions!C16+Assumptions!C17-Assumptions!C18 | C22: =Assumptions!D16+Assumptions!D17-Assumptions!D18 | D22: =Assumptions!E16+Assumptions!E17-Assumptions!E18 | E22: =Assumptions!F16+Assumptions!F17-Assumptions!F18 | F22: =Assumptions!G16+Assumptions!G17-Assumptions!G18
A23: Asset Turnover | B23: ='Income Statement'!C4/'Balance Sheet'!C17 | C23: ='Income Statement'!D4/'Balance Sheet'!D17 | D23: ='Income Statement'!E4/'Balance Sheet'!E17 | E23: ='Income Statement'!F4/'Balance Sheet'!F17 | F23: ='Income Statement'!G4/'Balance Sheet'!G17
A24: Cash Flow Ratios
A25: CFO / Net Profit | B25: ='Cash Flow Statement'!C11/'Income Statement'!C17 | C25: ='Cash Flow Statement'!D11/'Income Statement'!D17 | D25: ='Cash Flow Statement'!E11/'Income Statement'!E17 | E25: ='Cash Flow Statement'!F11/'Income Statement'!F17 | F25: ='Cash Flow Statement'!G11/'Income Statement'!G17
A26: Free Cash Flow (FCF) | B26: ='Cash Flow Statement'!C11+'Cash Flow Statement'!C15 | C26: ='Cash Flow Statement'!D11+'Cash Flow Statement'!D15 | D26: ='Cash Flow Statement'!E11+'Cash Flow Statement'!E15 | E26: ='Cash Flow Statement'!F11+'Cash Flow Statement'!F15 | F26: ='Cash Flow Statement'!G11+'Cash Flow Statement'!G15
A27: FCF / Revenue % | B27: =('Cash Flow Statement'!C11+'Cash Flow Statement'!C15)/'Income Statement'!C4 | C27: =('Cash Flow Statement'!D11+'Cash Flow Statement'!D15)/'Income Statement'!D4 | D27: =('Cash Flow Statement'!E11+'Cash Flow Statement'!E15)/'Income Statement'!E4 | E27: =('Cash Flow Statement'!F11+'Cash Flow Statement'!F15)/'Income Statement'!F4 | F27: =('Cash Flow Statement'!G11+'Cash Flow Statement'!G15)/'Income Statement'!G4
A28: Capex / Revenue % | B28: =-'Cash Flow Statement'!C13/'Income Statement'!C4 | C28: =-'Cash Flow Statement'!D13/'Income Statement'!D4 | D28: =-'Cash Flow Statement'!E13/'Income Statement'!E4 | E28: =-'Cash Flow Statement'!F13/'Income Statement'!F4 | F28: =-'Cash Flow Statement'!G13/'Income Statement'!G4
