Workbook

Sheet Assumptions
A1: 13-WEEK CASH FLOW MODEL — ASSUMPTIONS
A2: Blue cells = editable inputs | Black = formulas | All amounts in ₹
A3: 1. Opening Balance
A4: Opening Cash Balance (₹) | B4: 2500000 | C4: As at forecast start date
A5: 2. Cash Collections — Debtor Timing
A6: Weekly Base Sales (₹) | B6: 800000 | C6: Average weekly invoiced sales
A7: Weekly Sales Growth Rate | B7: 0.005 | C7: Week-on-week growth
A8: Collected — Same Week (%) | B8: 0.3 | C8: Cash received within 7 days
A9: Collected — Week +1 (%) | B9: 0.45 | C9: Payment in 8–14 days
A10: Collected — Week +2 (%) | B10: 0.2 | C10: Payment in 15–21 days
A11: Collected — Week +3 (%) | B11: 0.05 | C11: Payment beyond 21 days
A12: Other Income / Rebates — Weekly (₹) | B12: 50000 | C12: Freight rebates, misc income
A13: 3. Cash Outflows
A14: COGS as % of Sales | B14: 0.62 | C14: Materials + direct labour
A15: COGS Payment Lag (weeks) | B15: 1 | C15: Weeks after purchase
A16: Salaries & Wages — Weekly (₹) | B16: 180000 | C16: Fixed weekly payroll
A17: Rent & Utilities — Weekly (₹) | B17: 35000 | C17: Office + warehouse
A18: Freight & Logistics — Weekly (₹) | B18: 55000 | C18: EXIM / port costs
A19: Admin & Overheads — Weekly (₹) | B19: 25000 | C19: IT, stationery, misc
A20: Loan EMI — Weekly (₹) | B20: 40000 | C20: Bank loan repayment
A21: GST/Tax Payment — in Week # | B21: 4 | C21: Enter week number (1-13)
A22: GST/Tax Payment Amount (₹) | B22: 120000 | C22: Advance tax or GST outflow
A23: Capex / One-off — in Week # | B23: 8 | C23: Enter week number (1-13)
A24: Capex / One-off Amount (₹) | B24: 300000 | C24: Equipment / asset purchase
A25: 4. Liquidity Parameters
A26: Minimum Cash Buffer (₹) | B26: 500000 | C26: Alert if closing balance < this
A27: Overdraft Facility Available (₹) | B27: 1000000 | C27: Working capital line from bank
A28: 5. Forecast Period
A29: Forecast Start Date (Monday Wk1) | B29: 45782 | C29: First Monday of forecast

Sheet Sales Schedule
A1: SALES & COLLECTIONS SCHEDULE
A2: Item | B2: Wk 1 | C2: Wk 2 | D2: Wk 3 | E2: Wk 4 | F2: Wk 5 | G2: Wk 6 | H2: Wk 7 | I2: Wk 8 | J2: Wk 9 | K2: Wk 10 | L2: Wk 11 | M2: Wk 12 | N2: Wk 13 | O2: TOTAL
A3: Week Ending (Sunday) | B3: =Assumptions!$B$29+(1-1)*7+6 -> 45788 | C3: =Assumptions!$B$29+(2-1)*7+6 -> 45795 | D3: =Assumptions!$B$29+(3-1)*7+6 -> 45802 | E3: =Assumptions!$B$29+(4-1)*7+6 -> 45809 | F3: =Assumptions!$B$29+(5-1)*7+6 -> 45816 | G3: =Assumptions!$B$29+(6-1)*7+6 -> 45823 | H3: =Assumptions!$B$29+(7-1)*7+6 -> 45830 | I3: =Assumptions!$B$29+(8-1)*7+6 -> 45837 | J3: =Assumptions!$B$29+(9-1)*7+6 -> 45844 | K3: =Assumptions!$B$29+(10-1)*7+6 -> 45851 | L3: =Assumptions!$B$29+(11-1)*7+6 -> 45858 | M3: =Assumptions!$B$29+(12-1)*7+6 -> 45865 | N3: =Assumptions!$B$29+(13-1)*7+6 -> 45872
A4: Gross Sales (₹) | B4: =Assumptions!$B$6*(1+Assumptions!$B$7)^(1-1) -> 800000 | C4: =Assumptions!$B$6*(1+Assumptions!$B$7)^(2-1) -> 804000 | D4: =Assumptions!$B$6*(1+Assumptions!$B$7)^(3-1) -> 808020 | E4: =Assumptions!$B$6*(1+Assumptions!$B$7)^(4-1) -> 812060.1 | F4: =Assumptions!$B$6*(1+Assumptions!$B$7)^(5-1) -> 816120.4 | G4: =Assumptions!$B$6*(1+Assumptions!$B$7)^(6-1) -> 820201 | H4: =Assumptions!$B$6*(1+Assumptions!$B$7)^(7-1) -> 824302.01 | I4: =Assumptions!$B$6*(1+Assumptions!$B$7)^(8-1) -> 828423.52 | J4: =Assumptions!$B$6*(1+Assumptions!$B$7)^(9-1) -> 832565.64 | K4: =Assumptions!$B$6*(1+Assumptions!$B$7)^(10-1) -> 836728.46 | L4: =Assumptions!$B$6*(1+Assumptions!$B$7)^(11-1) -> 840912.11 | M4: =Assumptions!$B$6*(1+Assumptions!$B$7)^(12-1) -> 845116.67 | N4: =Assumptions!$B$6*(1+Assumptions!$B$7)^(13-1) -> 849342.25 | O4: =SUM(B4:N4) -> 10717792
A5: Same Week Collections (W+0) | B5: =B4*Assumptions!$B$8 -> 240000 | C5: =C4*Assumptions!$B$8 -> 241200 | D5: =D4*Assumptions!$B$8 -> 242406 | E5: =E4*Assumptions!$B$8 -> 243618.03 | F5: =F4*Assumptions!$B$8 -> 244836.12 | G5: =G4*Assumptions!$B$8 -> 246060.3 | H5: =H4*Assumptions!$B$8 -> 247290.6 | I5: =I4*Assumptions!$B$8 -> 248527.06 | ... N5: =N4*Assumptions!$B$8 -> 254802.67 | O5: =SUM(B5:N5) -> 3215337.6
A6: 1-Week Lag Collections (W+1) | B6: 0 | C6: =B4*Assumptions!$B$9 -> 360000 | D6: =C4*Assumptions!$B$9 -> 361800 | E6: =D4*Assumptions!$B$9 -> 363609 | F6: =E4*Assumptions!$B$9 -> 365427.04 | G6: =F4*Assumptions!$B$9 -> 367254.18 | H6: =G4*Assumptions!$B$9 -> 369090.45 | I6: =H4*Assumptions!$B$9 -> 370935.9 | J6: =I4*Assumptions!$B$9 -> 372790.58 | ... N6: =M4*Assumptions!$B$9 -> 380302.5 | O6: =SUM(B6:N6) -> 4440802.5
A7: 2-Week Lag Collections (W+2) | B7: 0 | C7: 0 | D7: =B4*Assumptions!$B$10 -> 160000 | E7: =C4*Assumptions!$B$10 -> 160800 | F7: =D4*Assumptions!$B$10 -> 161604 | G7: =E4*Assumptions!$B$10 -> 162412.02 | H7: =F4*Assumptions!$B$10 -> 163224.08 | I7: =G4*Assumptions!$B$10 -> 164040.2 | J7: =H4*Assumptions!$B$10 -> 164860.4 | K7: =I4*Assumptions!$B$10 -> 165684.7 | ... N7: =L4*Assumptions!$B$10 -> 168182.42 | O7: =SUM(B7:N7) -> 1804666.6
A8: 3-Week Lag Collections (W+3) | B8: 0 | C8: 0 | D8: 0 | E8: =B4*Assumptions!$B$11 -> 40000 | F8: =C4*Assumptions!$B$11 -> 40200 | G8: =D4*Assumptions!$B$11 -> 40401 | H8: =E4*Assumptions!$B$11 -> 40603.005 | I8: =F4*Assumptions!$B$11 -> 40806.02 | J8: =G4*Assumptions!$B$11 -> 41010.05 | K8: =H4*Assumptions!$B$11 -> 41215.1 | L8: =I4*Assumptions!$B$11 -> 41421.176 | ... N8: =K4*Assumptions!$B$11 -> 41836.423 | O8: =SUM(B8:N8) -> 409121.06
A9: TOTAL CASH COLLECTIONS (₹) | B9: =SUM(B5:B8) -> 240000 | C9: =SUM(C5:C8) -> 601200 | D9: =SUM(D5:D8) -> 764206 | E9: =SUM(E5:E8) -> 808027.03 | F9: =SUM(F5:F8) -> 812067.17 | G9: =SUM(G5:G8) -> 816127.5 | H9: =SUM(H5:H8) -> 820208.14 | I9: =SUM(I5:I8) -> 824309.18 | ... O9: =SUM(O5:O8) -> 9869927.8

Sheet Cash Flow Forecast
A1: 13-WEEK CASH FLOW FORECAST
A2: All amounts in Indian Rupees (₹) | Blue = inputs | Black = formulas | Green = cross-sheet links
A3: Description | B3: Week 1 | C3: Week 2 | D3: Week 3 | E3: Week 4 | F3: Week 5 | G3: Week 6 | H3: Week 7 | I3: Week 8 | J3: Week 9 | K3: Week 10 | L3: Week 11 | M3: Week 12 | N3: Week 13 | O3: 13-Wk TOTAL | P3: AVG/WK
A4: Week Ending (Sunday) | B4: ='Sales Schedule'!B3 -> 45788 | C4: ='Sales Schedule'!C3 -> 45795 | D4: ='Sales Schedule'!D3 -> 45802 | E4: ='Sales Schedule'!E3 -> 45809 | F4: ='Sales Schedule'!F3 -> 45816 | G4: ='Sales Schedule'!G3 -> 45823 | H4: ='Sales Schedule'!H3 -> 45830 | I4: ='Sales Schedule'!I3 -> 45837 | ... N4: ='Sales Schedule'!N3 -> 45872 | O4: — | P4: —
A5: OPENING CASH BALANCE
A6: Opening Cash Balance (₹) | B6: =Assumptions!$B$4 -> 2500000 | C6: =B23 -> 2455000 | D6: =C23 -> 2275200 | E6: =D23 -> 2255926 | F6: =E23 -> 2157980.6 | G6: =F23 -> 2181570.5 | H6: =G23 -> 2206703.4 | I6: =H23 -> 2233386.9 | J6: =I23 -> 1961628.8 | ... N6: =M23 -> 2090337.2 | O6: — | P6: =AVERAGE(B6:N6) -> 2183674.8
A7: A. CASH INFLOWS
A8: Cash Collections from Sales | B8: ='Sales Schedule'!B9 -> 240000 | C8: ='Sales Schedule'!C9 -> 601200 | D8: ='Sales Schedule'!D9 -> 764206 | E8: ='Sales Schedule'!E9 -> 808027.03 | F8: ='Sales Schedule'!F9 -> 812067.17 | G8: ='Sales Schedule'!G9 -> 816127.5 | H8: ='Sales Schedule'!H9 -> 820208.14 | I8: ='Sales Schedule'!I9 -> 824309.18 | ... N8: ='Sales Schedule'!N9 -> 845124.02 | O8: =SUM(B8:N8) -> 9869927.8 | P8: =AVERAGE(B8:N8) -> 759225.22
A9: Other Income / Rebates (₹) | B9: =Assumptions!$B$12 -> 50000 | C9: =Assumptions!$B$12 -> 50000 | D9: =Assumptions!$B$12 -> 50000 | E9: =Assumptions!$B$12 -> 50000 | F9: =Assumptions!$B$12 -> 50000 | G9: =Assumptions!$B$12 -> 50000 | H9: =Assumptions!$B$12 -> 50000 | I9: =Assumptions!$B$12 -> 50000 | ... N9: =Assumptions!$B$12 -> 50000 | O9: =SUM(B9:N9) -> 650000 | P9: =AVERAGE(B9:N9) -> 50000
A10: TOTAL CASH INFLOWS (A) | B10: =SUM(B8:B9) -> 290000 | C10: =SUM(C8:C9) -> 651200 | D10: =SUM(D8:D9) -> 814206 | E10: =SUM(E8:E9) -> 858027.03 | F10: =SUM(F8:F9) -> 862067.17 | G10: =SUM(G8:G9) -> 866127.5 | H10: =SUM(H8:H9) -> 870208.14 | I10: =SUM(I8:I9) -> 874309.18 | ... N10: =SUM(N8:N9) -> 895124.02 | O10: =SUM(B10:N10) -> 10519928 | P10: =AVERAGE(B10:N10) -> 809225.22
A11: B. CASH OUTFLOWS — PAYMENTS
A12: COGS / Purchases Payment (₹) | B12: =0 -> 0 | C12: ='Sales Schedule'!B4*Assumptions!$B$14 -> 496000 | D12: ='Sales Schedule'!C4*Assumptions!$B$14 -> 498480 | E12: ='Sales Schedule'!D4*Assumptions!$B$14 -> 500972.4 | F12: ='Sales Schedule'!E4*Assumptions!$B$14 -> 503477.26 | G12: ='Sales Schedule'!F4*Assumptions!$B$14 -> 505994.65 | H12: ='Sales Schedule'!G4*Assumptions!$B$14 -> 508524.62 | I12: ='Sales Schedule'!H4*Assumptions!$B$14 -> 511067.24 | J12: ='Sales Schedule'!I4*Assumptions!$B$14 -> 513622.58 | ... N12: ='Sales Schedule'!M4*Assumptions!$B$14 -> 523972.33 | O12: =SUM(B12:N12) -> 6118438.9 | P12: =AVERAGE(B12:N12) -> 470649.15
A13: Salaries & Wages (₹) | B13: =Assumptions!$B$16 -> 180000 | C13: =Assumptions!$B$16 -> 180000 | D13: =Assumptions!$B$16 -> 180000 | E13: =Assumptions!$B$16 -> 180000 | F13: =Assumptions!$B$16 -> 180000 | G13: =Assumptions!$B$16 -> 180000 | H13: =Assumptions!$B$16 -> 180000 | I13: =Assumptions!$B$16 -> 180000 | ... N13: =Assumptions!$B$16 -> 180000 | O13: =SUM(B13:N13) -> 2340000 | P13: =AVERAGE(B13:N13) -> 180000
A14: Rent & Utilities (₹) | B14: =Assumptions!$B$17 -> 35000 | C14: =Assumptions!$B$17 -> 35000 | D14: =Assumptions!$B$17 -> 35000 | E14: =Assumptions!$B$17 -> 35000 | F14: =Assumptions!$B$17 -> 35000 | G14: =Assumptions!$B$17 -> 35000 | H14: =Assumptions!$B$17 -> 35000 | I14: =Assumptions!$B$17 -> 35000 | ... N14: =Assumptions!$B$17 -> 35000 | O14: =SUM(B14:N14) -> 455000 | P14: =AVERAGE(B14:N14) -> 35000
A15: Freight & Logistics (₹) | B15: =Assumptions!$B$18 -> 55000 | C15: =Assumptions!$B$18 -> 55000 | D15: =Assumptions!$B$18 -> 55000 | E15: =Assumptions!$B$18 -> 55000 | F15: =Assumptions!$B$18 -> 55000 | G15: =Assumptions!$B$18 -> 55000 | H15: =Assumptions!$B$18 -> 55000 | I15: =Assumptions!$B$18 -> 55000 | ... N15: =Assumptions!$B$18 -> 55000 | O15: =SUM(B15:N15) -> 715000 | P15: =AVERAGE(B15:N15) -> 55000
A16: Admin & Overheads (₹) | B16: =Assumptions!$B$19 -> 25000 | C16: =Assumptions!$B$19 -> 25000 | D16: =Assumptions!$B$19 -> 25000 | E16: =Assumptions!$B$19 -> 25000 | F16: =Assumptions!$B$19 -> 25000 | G16: =Assumptions!$B$19 -> 25000 | H16: =Assumptions!$B$19 -> 25000 | I16: =Assumptions!$B$19 -> 25000 | ... N16: =Assumptions!$B$19 -> 25000 | O16: =SUM(B16:N16) -> 325000 | P16: =AVERAGE(B16:N16) -> 25000
A17: Loan / EMI Repayment (₹) | B17: =Assumptions!$B$20 -> 40000 | C17: =Assumptions!$B$20 -> 40000 | D17: =Assumptions!$B$20 -> 40000 | E17: =Assumptions!$B$20 -> 40000 | F17: =Assumptions!$B$20 -> 40000 | G17: =Assumptions!$B$20 -> 40000 | H17: =Assumptions!$B$20 -> 40000 | I17: =Assumptions!$B$20 -> 40000 | ... N17: =Assumptions!$B$20 -> 40000 | O17: =SUM(B17:N17) -> 520000 | P17: =AVERAGE(B17:N17) -> 40000
A18: GST / Tax Payment (₹) | B18: =IF(1=Assumptions!$B$21,Assumptions!$B$22,0) -> 0 | C18: =IF(2=Assumptions!$B$21,Assumptions!$B$22,0) -> 0 | D18: =IF(3=Assumptions!$B$21,Assumptions!$B$22,0) -> 0 | E18: =IF(4=Assumptions!$B$21,Assumptions!$B$22,0) -> 120000 | F18: =IF(5=Assumptions!$B$21,Assumptions!$B$22,0) -> 0 | G18: =IF(6=Assumptions!$B$21,Assumptions!$B$22,0) -> 0 | H18: =IF(7=Assumptions!$B$21,Assumptions!$B$22,0) -> 0 | I18: =IF(8=Assumptions!$B$21,Assumptions!$B$22,0) -> 0 | J18: =IF(9=Assumptions!$B$21,Assumptions!$B$22,0) -> 0 | K18: =IF(10=Assumptions!$B$21,Assumptions!$B$22,0) -> 0 | L18: =IF(11=Assumptions!$B$21,Assumptions!$B$22,0) -> 0 | M18: =IF(12=Assumptions!$B$21,Assumptions!$B$22,0) -> 0 | N18: =IF(13=Assumptions!$B$21,Assumptions!$B$22,0) -> 0 | O18: =SUM(B18:N18) -> 120000 | P18: =AVERAGE(B18:N18) -> 9230.7692
A19: Capex / One-off Expenditure (₹) | B19: =IF(1=Assumptions!$B$23,Assumptions!$B$24,0) -> 0 | C19: =IF(2=Assumptions!$B$23,Assumptions!$B$24,0) -> 0 | D19: =IF(3=Assumptions!$B$23,Assumptions!$B$24,0) -> 0 | E19: =IF(4=Assumptions!$B$23,Assumptions!$B$24,0) -> 0 | F19: =IF(5=Assumptions!$B$23,Assumptions!$B$24,0) -> 0 | G19: =IF(6=Assumptions!$B$23,Assumptions!$B$24,0) -> 0 | H19: =IF(7=Assumptions!$B$23,Assumptions!$B$24,0) -> 0 | I19: =IF(8=Assumptions!$B$23,Assumptions!$B$24,0) -> 300000 | J19: =IF(9=Assumptions!$B$23,Assumptions!$B$24,0) -> 0 | K19: =IF(10=Assumptions!$B$23,Assumptions!$B$24,0) -> 0 | L19: =IF(11=Assumptions!$B$23,Assumptions!$B$24,0) -> 0 | M19: =IF(12=Assumptions!$B$23,Assumptions!$B$24,0) -> 0 | N19: =IF(13=Assumptions!$B$23,Assumptions!$B$24,0) -> 0 | O19: =SUM(B19:N19) -> 300000 | P19: =AVERAGE(B19:N19) -> 23076.923
A20: TOTAL CASH OUTFLOWS (B) | B20: =SUM(B12:B19) -> 335000 | C20: =SUM(C12:C19) -> 831000 | D20: =SUM(D12:D19) -> 833480 | E20: =SUM(E12:E19) -> 955972.4 | F20: =SUM(F12:F19) -> 838477.26 | G20: =SUM(G12:G19) -> 840994.65 | H20: =SUM(H12:H19) -> 843524.62 | I20: =SUM(I12:I19) -> 1146067.2 | ... N20: =SUM(N12:N19) -> 858972.33 | O20: =SUM(B20:N20) -> 10893439 | P20: =AVERAGE(B20:N20) -> 837956.84
A21: C. NET CASH FLOW & POSITION
A22: NET CASH FLOW (A minus B) | B22: =B10-B20 -> -45000 | C22: =C10-C20 -> -179800 | D22: =D10-D20 -> -19274 | E22: =E10-E20 -> -97945.37 | F22: =F10-F20 -> 23589.903 | G22: =G10-G20 -> 25132.853 | H22: =H10-H20 -> 26683.517 | I22: =I10-I20 -> -271758.07 | ... N22: =N10-N20 -> 36151.686 | O22: =SUM(B22:N22) -> -373511.14 | P22: =AVERAGE(B22:N22) -> -28731.626
A23: CLOSING CASH BALANCE (₹) | B23: =B6+B22 -> 2455000 | C23: =C6+C22 -> 2275200 | D23: =D6+D22 -> 2255926 | E23: =E6+E22 -> 2157980.6 | F23: =F6+F22 -> 2181570.5 | G23: =G6+G22 -> 2206703.4 | H23: =H6+H22 -> 2233386.9 | I23: =I6+I22 -> 1961628.8 | ... N23: =N6+N22 -> 2126488.9 | O23: =SUM(B23:N23) -> 28014262 | P23: =AVERAGE(B23:N23) -> 2154943.2
A24: D. LIQUIDITY ALERTS
A25: Buffer Status (✓ OK / ⚠ LOW) | B25: =IF(B23<Assumptions!$B$26,"⚠ LOW","✓ OK") -> ✓ OK | C25: =IF(C23<Assumptions!$B$26,"⚠ LOW","✓ OK") -> ✓ OK | D25: =IF(D23<Assumptions!$B$26,"⚠ LOW","✓ OK") -> ✓ OK | E25: =IF(E23<Assumptions!$B$26,"⚠ LOW","✓ OK") -> ✓ OK | F25: =IF(F23<Assumptions!$B$26,"⚠ LOW","✓ OK") -> ✓ OK | G25: =IF(G23<Assumptions!$B$26,"⚠ LOW","✓ OK") -> ✓ OK | H25: =IF(H23<Assumptions!$B$26,"⚠ LOW","✓ OK") -> ✓ OK | I25: =IF(I23<Assumptions!$B$26,"⚠ LOW","✓ OK") -> ✓ OK | ... N25: =IF(N23<Assumptions!$B$26,"⚠ LOW","✓ OK") -> ✓ OK | O25: =COUNTIF(B25:N25,"⚠ LOW")&" low weeks" -> 0 low weeks
A26: Cumulative Net Cash Flow (₹) | B26: =SUM($B$22:B22) -> -45000 | C26: =SUM($B$22:C22) -> -224800 | D26: =SUM($B$22:D22) -> -244074 | E26: =SUM($B$22:E22) -> -342019.37 | F26: =SUM($B$22:F22) -> -318429.47 | G26: =SUM($B$22:G22) -> -293296.61 | H26: =SUM($B$22:H22) -> -266613.1 | I26: =SUM($B$22:I22) -> -538371.16 | ... N26: =SUM($B$22:N22) -> -373511.14 | O26: =N26 -> -373511.14
A27: Minimum Closing Balance (13-wk) | B27: =MIN(B23:N23) -> 1961628.8
A28: Maximum Closing Balance (13-wk) | B28: =MAX(B23:N23) -> 2455000
A29: E. SUMMARY STATISTICS
A30: Total Cash Inflows (13 weeks) | B30: =SUM(B10:N10) -> 10519928
A31: Total Cash Outflows (13 weeks) | B31: =SUM(B20:N20) -> 10893439
A32: Net Cash Generated | B32: =B30-B31 -> -373511.14
A33: Average Weekly Net Cash Flow | B33: =B32/13 -> -28731.626
A34: Weeks with Positive Net Flow | B34: =COUNTIF(B22:N22,">0") -> 8
A35: Weeks Below Minimum Buffer | B35: =COUNTIF(B23:N23,"<"&Assumptions!$B$26) -> 0

Sheet Charts
A1: CHART DATA — Cash Flow Visualisation
A2: Metric | B2: Wk 1 | C2: Wk 2 | D2: Wk 3 | E2: Wk 4 | F2: Wk 5 | G2: Wk 6 | H2: Wk 7 | I2: Wk 8 | J2: Wk 9 | K2: Wk 10 | L2: Wk 11 | M2: Wk 12 | N2: Wk 13 | O2: Total
A3: Opening Balance | B3: ='Cash Flow Forecast'!B6 -> 2500000 | C3: ='Cash Flow Forecast'!C6 -> 2455000 | D3: ='Cash Flow Forecast'!D6 -> 2275200 | E3: ='Cash Flow Forecast'!E6 -> 2255926 | F3: ='Cash Flow Forecast'!F6 -> 2157980.6 | G3: ='Cash Flow Forecast'!G6 -> 2181570.5 | H3: ='Cash Flow Forecast'!H6 -> 2206703.4 | I3: ='Cash Flow Forecast'!I6 -> 2233386.9 | ... O3: ='Cash Flow Forecast'!O6 -> —
A4: Total Inflows | B4: ='Cash Flow Forecast'!B10 -> 290000 | C4: ='Cash Flow Forecast'!C10 -> 651200 | D4: ='Cash Flow Forecast'!D10 -> 814206 | E4: ='Cash Flow Forecast'!E10 -> 858027.03 | F4: ='Cash Flow Forecast'!F10 -> 862067.17 | G4: ='Cash Flow Forecast'!G10 -> 866127.5 | H4: ='Cash Flow Forecast'!H10 -> 870208.14 | I4: ='Cash Flow Forecast'!I10 -> 874309.18 | ... O4: ='Cash Flow Forecast'!O10 -> 10519928
A5: Total Outflows | B5: ='Cash Flow Forecast'!B20 -> 335000 | C5: ='Cash Flow Forecast'!C20 -> 831000 | D5: ='Cash Flow Forecast'!D20 -> 833480 | E5: ='Cash Flow Forecast'!E20 -> 955972.4 | F5: ='Cash Flow Forecast'!F20 -> 838477.26 | G5: ='Cash Flow Forecast'!G20 -> 840994.65 | H5: ='Cash Flow Forecast'!H20 -> 843524.62 | I5: ='Cash Flow Forecast'!I20 -> 1146067.2 | ... O5: ='Cash Flow Forecast'!O20 -> 10893439
A6: Net Cash Flow | B6: ='Cash Flow Forecast'!B22 -> -45000 | C6: ='Cash Flow Forecast'!C22 -> -179800 | D6: ='Cash Flow Forecast'!D22 -> -19274 | E6: ='Cash Flow Forecast'!E22 -> -97945.37 | F6: ='Cash Flow Forecast'!F22 -> 23589.903 | G6: ='Cash Flow Forecast'!G22 -> 25132.853 | H6: ='Cash Flow Forecast'!H22 -> 26683.517 | I6: ='Cash Flow Forecast'!I22 -> -271758.07 | ... O6: ='Cash Flow Forecast'!O22 -> -373511.14
A7: Closing Balance | B7: ='Cash Flow Forecast'!B23 -> 2455000 | C7: ='Cash Flow Forecast'!C23 -> 2275200 | D7: ='Cash Flow Forecast'!D23 -> 2255926 | E7: ='Cash Flow Forecast'!E23 -> 2157980.6 | F7: ='Cash Flow Forecast'!F23 -> 2181570.5 | G7: ='Cash Flow Forecast'!G23 -> 2206703.4 | H7: ='Cash Flow Forecast'!H23 -> 2233386.9 | I7: ='Cash Flow Forecast'!I23 -> 1961628.8 | ... O7: ='Cash Flow Forecast'!O23 -> 28014262
A8: Cumulative NCF | B8: ='Cash Flow Forecast'!B26 -> -45000 | C8: ='Cash Flow Forecast'!C26 -> -224800 | D8: ='Cash Flow Forecast'!D26 -> -244074 | E8: ='Cash Flow Forecast'!E26 -> -342019.37 | F8: ='Cash Flow Forecast'!F26 -> -318429.47 | G8: ='Cash Flow Forecast'!G26 -> -293296.61 | H8: ='Cash Flow Forecast'!H26 -> -266613.1 | I8: ='Cash Flow Forecast'!I26 -> -538371.16 | ... O8: ='Cash Flow Forecast'!O26 -> -373511.14
